tcms_github_app/__init__.py
tcms_github_app/admin.py
tcms_github_app/issues.py
tcms_github_app/menu.py
tcms_github_app/middleware.py
tcms_github_app/models.py
tcms_github_app/urls.py
tcms_github_app/utils.py
tcms_github_app/views.py
tcms_github_app/migrations/0001_initial.py
tcms_github_app/migrations/0002_appinstallation_settings_url.py
tcms_github_app/migrations/0003_models_jsonfield.py
tcms_github_app/migrations/__init__.py
tcms_settings_dir/__init__.py
tcms_settings_dir/github_app.py
kiwitcms_github_app-2.1.0.dist-info/LICENSE
kiwitcms_github_app-2.1.0.dist-info/METADATA
kiwitcms_github_app-2.1.0.dist-info/WHEEL
kiwitcms_github_app-2.1.0.dist-info/entry_points.txt
kiwitcms_github_app-2.1.0.dist-info/top_level.txt
kiwitcms_github_app-2.1.0.dist-info/RECORD
