Metadata-Version: 2.2
Name: kiwitcms-github-app
Version: 2.1.0
Summary: GitHub App integration for Kiwi TCMS
Home-page: https://github.com/kiwitcms/github-app/
Author: Kiwi TCMS
Author-email: info@kiwitcms.org
License: AGPLv3+
Classifier: Framework :: Django
Classifier: Development Status :: 5 - Production/Stable
Classifier: Topic :: Software Development :: Quality Assurance
Classifier: Topic :: Software Development :: Testing
Classifier: Environment :: Web Environment
Classifier: Intended Audience :: Developers
Classifier: License :: OSI Approved :: GNU Affero General Public License v3 or later (AGPLv3+)
Classifier: Programming Language :: Python :: 3
Classifier: Programming Language :: Python :: 3.8
Classifier: Programming Language :: Python :: 3.11
License-File: LICENSE
Requires-Dist: social-auth-app-django
Requires-Dist: social-auth-core>=3.3.0
Requires-Dist: kiwitcms-tenants
Requires-Dist: certifi>=2023.7.22
Requires-Dist: cryptography>=41.0.4
Requires-Dist: pyjwt>=2.4.0
Requires-Dist: requests>=2.32.0
Requires-Dist: sqlparse>=0.5.0
Dynamic: author
Dynamic: author-email
Dynamic: classifier
Dynamic: description
Dynamic: home-page
Dynamic: license
Dynamic: requires-dist
Dynamic: summary
